{
    "simple-list": [{
        "text": "Option 1",
        "value": "option1"
    }, {
        "text": "Option 2",
        "value": "option2"
    }, {
        "text": "Option 3",
        "value": "option3"
    }],
    "distinct-list": [
        {"text": "Apple", "value": "apple"},
        {"text": "Orange", "value": "orange"},
        {"text": "Banana", "value": "banana"},
        {"text": "Grapes", "value": "grapes"},
        {"text": "Melon", "value": "melon"},
        {"text": "Mango", "value": "mango"},
        {"text": "Mango Raw", "value": "mangoraw"},
        {"text": "Avacado", "value": "avacado"}
    ]
}
